libpythonpro_junior/__init__.py
libpythonpro_junior/github_api.py
libpythonpro_junior-0.2.dist-info/LICENSE
libpythonpro_junior-0.2.dist-info/METADATA
libpythonpro_junior-0.2.dist-info/WHEEL
libpythonpro_junior-0.2.dist-info/top_level.txt
libpythonpro_junior-0.2.dist-info/RECORD
