Metadata-Version: 2.1
Name: libpythonpro-junior
Version: 0.2
Summary: Módulo para exemplificar construção de projeto Python no curso PyTools
Home-page: https://github.com/IsaelDJunior/libpythonpro_junior
Author: Isael Dorneles Junior
Author-email: isaeldjunior@gmail.com
License: GNU AFFERO GENERAL PUBLIC LICENSE
Platform: UNKNOWN
Classifier: Development Status :: 2 - Pre-Alpha
Classifier: Environment :: Console
Classifier: Intended Audience :: Developers
Classifier: License :: OSI Approved :: GNU Affero General Public License v3 or later (AGPLv3+)
Classifier: Operating System :: OS Independent
Classifier: Programming Language :: Python
Classifier: Programming Language :: Python :: 3.9
Classifier: Framework :: Pytest
License-File: LICENSE
Requires-Dist: requests
